[1,["ecpdLyjvZBwrvm+cedCcQy","ebPEn8Od5GF4xRQXc+wKxM","8f8K936H9LK6csUSLz0Tig","afgFVwBz5GH5lVby0jARfS","6dPM3jr4dDl5p4jpYKoj2p","5b6nuFnetC4Yo3Nis4Qw+7","a4Lddo9hdK1rTHjVFGOVa2","69MDdRby1G4axqkEg9ZbX8"],["node","root","label","_N$target","target","data","_spriteFrame"],[["cc.AnimationClip",["_name","_duration","wrapMode","sample","curveData"],-1,11],["cc.PrefabInfo",["fileId","root","asset"],2,1,1],["cc.AnimationClip",["_name","_duration","wrapMode","curveData"],-1],["cc.Prefab",["_name"],2],["cc.Node",["_name","_children","_components","_prefab","_contentSize"],2,2,9,4,5],["cc.Node",["_name","_parent","_components","_prefab","_color","_contentSize"],2,1,2,4,5,5],["cc.Sprite",["_sizeMode","node","_materials","_spriteFrame"],2,1,3,6],["f46cchEtUxBQp4THmPhpjJ4",["node","label"],3,1,1],["cc.Button",["node","clickEvents","_N$target"],3,1,9,1],["cc.ClickEvent",["_componentId","handler","target"],1,1],["cc.Animation",["node","_clips"],3,1,3],["cc.Label",["_string","_fontSize","_lineHeight","_N$horizontalAlign","_N$verticalAlign","node","_materials"],-2,1,3]],[[2,0,1,2,3,5],[0,0,1,3,2,4,5],[0,0,1,2,4,4],[3,0,2],[4,0,1,2,3,4,2],[5,0,1,2,3,4,5,2],[6,0,1,2,3,2],[7,0,1,1],[8,0,1,2,1],[9,0,1,2,3],[10,0,1,1],[1,1,2,1],[1,0,1,2,2],[11,0,1,2,3,4,5,6,6]],[[[[0,"word_rotate2",3,2,{"paths":{"Label":{"props":{"angle":[{"frame":0,"value":0},{"frame":3,"value":-360}]}}}}]],0,0,[],[],[]],[[[1,"word_scale2",0.5,6,22,[{},"paths",11,[{},"Label",11,[{},"props",11,[{},"scale",12,[[[{"frame":0},"value",8,[1,1,1,1]],[{"frame":0.5},"value",8,[1,0.8,0.8,1]]],11,11]]]]]]],0,0,[],[],[]],[[[2,"word_all",3.0166666666666666,2,[{},"paths",11,[{},"Label",11,[{},"props",11,[{"angle":[{"frame":0,"value":0},{"frame":3.0166666666666666,"value":360}]},"scale",12,[[[{"frame":0},"value",8,[1,1,1,1]],[{"frame":0.48333333333333334},"value",8,[1,1.2,1.2,1]],[{"frame":0.9833333333333333},"value",8,[1,1,1,1]],[{"frame":1.5166666666666666},"value",8,[1,1.2,1.2,1]],[{"frame":2},"value",8,[1,1,1,1]],[{"frame":2.4833333333333334},"value",8,[1,1.2,1.2,1]],[{"frame":3},"value",8,[1,1,1,1]]],11,11,11,11,11,11,11]]]]]]],0,0,[],[],[]],[[[1,"word_scale",0.5,6,22,[{"props":{"scale":[]}},"paths",11,[{},"Label",11,[{},"props",11,[{},"scale",12,[[[{"frame":0},"value",8,[1,1,1,1]],[{"frame":0.5},"value",8,[1,1.2,1.2,1]]],11,11]]]]]]],0,0,[],[],[]],[[[2,"word_all2",3,2,[{},"paths",11,[{},"Label",11,[{},"props",11,[{"angle":[{"frame":0,"value":0},{"frame":3,"value":-360}]},"scale",12,[[[{"frame":0},"value",8,[1,1,1,1]],[{"frame":0.5},"value",8,[1,1.2,1.2,1]],[{"frame":1},"value",8,[1,1,1,1]],[{"frame":1.5},"value",8,[1,1.2,1.2,1]],[{"frame":2},"value",8,[1,1,1,1]],[{"frame":2.5},"value",8,[1,1.2,1.2,1]],[{"frame":3},"value",8,[1,1,1,1]]],11,11,11,11,11,11,11]]]]]]],0,0,[],[],[]],[[[3,"WordItem"],[4,"WordItem",[-9],[[6,0,-2,[1],2],[7,-4,-3],[8,-7,[[9,"f46cchEtUxBQp4THmPhpjJ4","onClick",-6]],-5],[10,-8,[3,4,5,6,7,8]]],[11,-1,0],[5,100,100]],[5,"Label",1,[-10],[12,"47JoG5pBBFjLV3uLFahTZf",1,0],[4,4280821879],[5,48,60.48]],[13,"好",48,48,1,1,2,[0]]],0,[0,1,1,0,0,1,0,2,3,0,0,1,0,3,1,0,4,1,0,0,1,0,0,1,0,-1,2,0,-1,3,0,5,1,10],[0,0,0,0,0,0,0,0,0],[-1,-1,6,-1,-2,-3,-4,-5,-6],[0,0,1,2,3,4,5,6,7]],[[[0,"word_rotate",3,2,{"paths":{"Label":{"props":{"angle":[{"frame":0,"value":0},{"frame":3,"value":360}]}}}}]],0,0,[],[],[]]]]