{"paths":{"0":["bg",3],"1":["icons",3],"2":["res",3],"3":["prefab/Toast",6],"4":["anim/fan",2],"5":["anim/cloud2",2],"6":["icons",5],"7":["anim/bottomOut",2],"8":["anim/toast",2],"9":["Specular",0],"10":["Specular",1],"11":["bg",4,1],"12":["anim/sun",2],"13":["anim/sunshine",2],"14":["prefab/WordItem",6],"15":["res",5],"16":["anim/cloud1",2],"17":["prefab/LevelItem",6],"18":["anim/sprIn1",2],"19":["anim/bottomIn",2],"20":["anim/sprIn2",2]},"types":["cc.EffectAsset","cc.Material","cc.AnimationClip","cc.Texture2D","cc.SpriteFrame","cc.SpriteAtlas","cc.Prefab"],"uuids":["54zMmbkRRKuIaNpKI3TCQe","5cZrpDMv9BOKCoCkHgagb5","7at9AgIotN8KJIjI40rFLr","0cRHpQqm1DdrdMkqdLDzbz","27uZ64B7hKi5G8wUyehksd","5cRl2dAu1F5K2XLcg4gcS+","67h+36BsNOz60zLFxTPegz","67nREFqWlDNq1XlV29+3CD","76KbPMgwtP5KkNcs4P6vbr","80dyaqaC1P3J7ZTueJmZzj","85yaF1ZuVPmK0ZVJFXS2UC","90odNuhPpDXq/urP4g1wUR","94DQ89BIZFDJY2ptUjBXGI","aatx2gSZxJzowO88QY7T9H","adz2/yGBZOzKrAmEvehVOO","bfhFE/I+FGRKEnp1PEHNGt","ea4lVxIrpDnoBkVIM78y0c","efqSPF6aNBuIflgGLihIKT","f3o1ohu/tMUo1LvYhlruDO","f5iMFMkbJAxIkewbPoQSCu","f9hXcp4txAf64kbbuh8Mv7","00mcUzeFJMhaByh8mbfZ9u","01VXpXI+BLfquw50o8ikD/","04f4EC5f9OkJzDZC9mrYzk","05KB7q0QVBd6iq4Dx4wEGD","05Q9PrSVhPXKa9ED5eilMW","06DKQjZelPu6FDfoP/lc27","06Sod0/3xKoqKq00xL9GNQ","08cZTAQPxP+qtBATrOZWgC","08up7CLGJBs5rzrpe8Zjhx","0a4+ZXa+RCTr6BcYcBPFM7","0caifTQxdH5Z5w2hKXhvnr","0cmY/jXH1FWIo5kZmJbAXV","0dDnWvgXVCG7Uj++NDSbKe","0eF0HD1BBCgZnMQTGZ6m4w","0eLpkMXQNDB4uUA5ofWPoy","0fxEf406FGb4BtD/lZapUY","12X2D1Iw1MEIdflqL3Qz0l","15OAH2DOlK95gGjLa28QZj","155GjywB1MuLim/HLfEDLv","16LFfUjzJAQohOrBpyiYpK","17BM7gP9VDrK5CzklDzW0d","18jHt4j3hN6aWkNdDuKd1q","1888lYFGRAt5EHSo0kFAOq","19uMr+yBpLTYDXCHFjItWh","1arVnziBJNmrnxuwcOCWqe","1bFBd6pN1DFaEgXrxUyFFZ","1bIQsHdA9AWLsoc3JZuy9F","1bKXQoVz5DZ4qNZi3jGDs6","1bsosQqxtHyayNF5xhLNl5","1dXLsiM0JALbf+Juh+2P5h","1emsTX4TRBeISFEUYhfFnw","21mECyGMFMDLfeYL4dNG51","259ytoRcBCR6j0VDBJOJMr","27zK5qZO9Dm6JuQ2qDZH0j","274/MB40NA6574MUFXYcOD","28hVD52MlNN4JfMtQiam4R","29PzcPrUNNgYXb2EaOQgbS","29QFFdEH1IwpT2Hlw/MS9f","29jfXH8xxHF6uVwCFPBBQ7","2bGfcN5iJHbqP4zBV3OoGF","2cwTTklMtPP7ghrpIdqrjO","2c2ik3VplOh7jedewKH6N7","2dOD3YjP5OwoWtwMr+WGTq","2fycJK7YVHsqT8yAvZ3YO3","2f0D7j3k5LlrDJbLAo1MZa","30QAXQW65KE4VQe45OFyRE","30rou4SX5NuoNR3Nugqpoj","3186Lz8xxPlY9xWlOIE3Wi","32WlGHLZhP2K2JL/YhWMpO","32t9t/DFxIvpnYRGPaESGX","336vcOtHtJvZVOshtbP0xR","35uZZcprZImpqTB+/5Ij4t","35+LYZ2PtMwYQrADbLdHkW","36lndk6QdNbasoh9md2SAQ","37lrkWOBVLEJl7hH12FkG0","373rIk/A1JvLbgXJoxwFNQ","38PX6y+gVNAZ0wzCAv9Th2","39atMLSQBMN4i3pzKiXc1u","3aOHLVbtVA9rbaAUX0f/AA","3aRYz+W59KYL1P/9znlKpB","3enKIyzpRFCIGQE3oYPw0C","40hB9wXH1FpbPix16kZ5Ap","40ssY63rZBBr/qe7Fdqfbd","41gL+Tg3NCp7mqL0ZUM6Zo","43vRNrWAVORLZYzY0QAKiZ","45IzZ1s7BPJ7lU6/xr06aG","46XtOB9rtBnr0S9B4VorVM","46q1RXrx9Hp4Bnz6I7mTky","462WpBlehHfq2e6xZXSfo6","48DKAFNeNDTIrsY9lpTjFJ","48vXjzGCdFab/ITlQhv+32","49wEkoOlxMdZv2U8y78jne","4aXeYodANKe5KYiZlMmSTH","4b9DJfDdZM8ppHyA+BkRLo","4eH0cqq/NMjr9hlVOg4VxE","50MjUVTilDSrtK5ekIc6ft","51aewvilFCU4f8ODAsa3xd","52T/vHrt9EyaXr3AtkdR3Y","54SbtHlhBHXbpXtgz6X2j4","54oS3j/uhDp7zs4AtLCHcl","545BaZiqVHf65q2Dfpmm1W","56eMBPVPFCPbS4SAjUQv93","56elBUS4JDZ7u10VkjA9nE","58wR8MyGZKJoenxAdLd9u1","5a7ILlYcpAIoxeETfsWZ5W","5dKCvq8n9HBog7pUswN5dm","60CYRwtopKyqUdb5AZK5N2","60U5XavFFPTLUok1rli5Q4","61LQbcHR1OGINBopEG71lH","62ki17MDNFPab6ND+KAj9Z","63HjZPN8RHsb7NkqyGRvC2","64CoxKCmFGxYm6oit/J5Uj","647p1aiHVI84emdK1NdT+R","65euz7gOhCdb+OgdoxsYPV","67Q2Ne/lVJ2qUhYMlbON/L","69EpOSi+VINYEst5c0TMUp","69qTI4JmBIBZ00IzirpUYF","6aYWCG1r5K6LqPIZtrqk/q","6arGOR8zFOy7D42F+ZiwkO","6cFSaRN19IRYaWCGQh9BAE","6fGMYgUX5H9quGNDeoF8VQ","71aOv5Ps5N6JYkz/2waTbT","74rp8KRW9A9oeoio9YYHeX","76BGVpRJpHwoA+hGdRXOr/","79CBbT42tKsYoVh9m5gLD8","79+NgL+8RJlIl5EXtk+Fe8","79/Yo3IrRA+bM8SMQ8eRPZ","7aXY1iQsNOl4BvC3kYZUNB","7afQu/txFNF6VQvU9mi2UF","7dfuLjOUZJG5XgQaKEpxvh","80Ile8rhlBi6tBQm/OPbjh","82NeXq6jZDFo0kExLBL2Se","82/MYavKpG15m1jejFAlcJ","83qqSxwb5J5Jio1OGL7GoS","88EZBkJNNKapiXqhavVaE4","8cqDpg2iRO7ao1TW7Si6hs","8cu59zG3xLcIHN6Ia9bVVQ","8d247/fJJN8qU2sV5RTE3P","8eMhZjov1Lm4QhT9iEvdw7","8ejAnTSrVKRLHCnCuLXsKP","8erm6/ha5L4LcJ+kzWxpUG","916tmbUwBIxITbqNwgItlj","95QvX3gdtEF5+QmSW/CTOF","96JuJX5NBDbpp1zJdTWWvk","98dxo/bMBBWLOcnm3chQIn","99FbWKEWtKV6waLf3imA4q","9dFAlaEYJAbLKUAFNSer66","9eRY0BbsFD4pVb8Zz3ICsK","9egv0dUYlGJ5oSPjIqsbCk","9ehVsXoXBJ8YoIr1VoMcVq","9fpm9IvbJDUIo5AJ2Rv6K/","a5P3LrF9xK0YaLS/DSqTql","a5kJlHxo9O4Ikq9yOi+J6K","a54f5dYEtOJJ/FNMV+13sY","a6NuztB8dH6JB3hMASrFOu","a8DmJArqZPIaEIsMT0FOzn","a95zrdtVhJbaDxTSNVPr53","aatUj91R9DroeQUSnQ4xH5","aa2CwDEIFKYJ2ywBQZBkIE","abD5mpBONLSZqLY8m3PCbt","acM4eDnM1KCZ6kt70vMsTX","adaIYp/xRF+pwrW0VIs4Qj","b5QVTkML1IlagfxzczUDTa","b6Rp5kM0tISpJ7UHctSGio","b8ecNiuFJDU5Uz2YVOOlw7","b9Ly6huE5Ov6AiWcXaVznf","b9N1CcugxGxI7gJ/v4hF7U","bbSqcOTNhDo4qHocctMY3Y","bbUY1Ct0NP9pFRLlwciMBN","bezPGQbhxAu59HIOL2rKkJ","be5P+dtERM74/524LEUpn9","bf0lzBaY9BxaoD43kBpCIi","c0v3LStqdM5I+4bK4uLEXB","c1C7scK1FFDY02dx7HVlX+","c2XNZz0lBDm6tttdPGQ9M+","c2bWcuHPxGiI5BPbE+WbSG","c483P9UEVDf6EIok9kKFfn","c499ErpRZPS4xrpQRQia/F","c56UxOI91CErNGhVP7D4kl","c59unTDTtBX7pJEGC4DDGs","c6I6/DsjxASJ76Xs3Vxy7+","c8Jtkb2otGp6SeSyntRpXi","c824MA7SpM4pRUajARlPst","c9N0lV1H1Ez7gkxMDRWyfA","cdKEH9AjZCML9IyTkhev+x","cd7r9N8lJLGZtpyCHKDLUz","d0AgASosdM/plwM3Uzmoop","d0OoaQAp1NRor0ITAaL+Qx","d4W6p4VhZOzabyxXj8Pk+x","d6uVSsCo5JMYhIgtMhwVWf","d66DVR8N9FBKnIKjFL+Ge3","ddGRTlK3lAc5f4gdHEE38L","deInfdNMNBR5fiJKPCcc7G","e0BW8Ev5JKeqrTysUC/NbJ","e34CXF5MdLT4+Gw1qiboT1","e7YzfrPHpBnJFr+VEuhtoA","e9YfQPWGdFg6nFQ7UOfhMv","eafItc28tMPrrBoT8+SZHS","ean7Lke7xKGJ4JGUst44cR","ebPEn8Od5GF4xRQXc+wKxM","ebfeE0tBBBjJrYaMq3u38v","ecpdLyjvZBwrvm+cedCcQy","edZ4ZLYX9KqJWIwJw6kDDL","ee/QwCvpBGmIc/Ddun4XMC","f1Kd+wHGpKd4Bl4r9HsAdU","f1YPnDJh5OnbqQ/5Wc5b2S","f19LqhjVBK26miOsuaA9D+","f1+hIHMchBf7FznK/9k6Gk","f4fTXoAjlBGoqZ/34qh8xs","f4ggvCcK5P5q2vgNJZgshh","f5SHMt4dBHGJZ6BMXk5CNn","f7F0E0ZyhMbIh8guVuFyAr","f7bnsdDFtEbZaNUpU07Gb2","f7jbWwEWZMeppl3V8OdNsa","fbFPAd5VxKjoBHZHLzKEjJ","fbfLhqqNRLYKroDcuhViyC","fb32JA5slEn5jakwcdiRyg","fcD65xYTdKc6Rdj3Z2Uu5n","fcH7c+TSFD/b4tiK733Rr0","fdlZjmiYFCi6lxDU1p0trq","feqMZDfFlAX5NmUtCxnNqb"],"scenes":{},"redirect":[202,0],"deps":["internal"],"packs":{"03202c618":[22,23,24,25,26,27,28,29,31,33,34,36,37,38,39,40,41,42,43,44,45,46,47,48,49,50,51,53,54,55,56,57,58,59,60,61,62,63,65,66,67,68,69,70,71,72,73,74,75,76,77,78,79,80,81,83,84,85,87,88,89,91,92,93,94,95,98,99,100,101,102,103,104,105,106,108,109,110,111,112,113,115,6,117,118,119,120,121,122,123,124,125,126,127,128,129,130,131,132,133,134,135,137,138,139,140,141,142,143,144,145,147,148,149,150,151,152,153,155,156,157,158,159,160,161,162,163,164,165,166,167,168,169,170,171,172,173,174,175,177,178,179,180,181,182,183,184,185,186,187,188,189,190,191,192,193,194,195,196,197,198,199,201,203,204,205,206,207,208,209,210,211,212,213,214,215,216,217,219,220,221],"085874ff0":[9,10],"0d8b04729":[32,35,52,64,82,86,90,97,107,114,116,146,154,15,176,218],"0e8434871":[0,1,2],"0f6fa3996":[3,8],"0f7bb46f0":[21,96]},"name":"resources","importBase":"import","nativeBase":"native","debug":false,"isZip":false,"encrypted":false,"versions":{"import":["03202c618","4d2f2","085874ff0","9cf9d",30,"d511b","0d8b04729","28987","0e8434871","c36e8","0f6fa3996","6252e","0f7bb46f0","a6aa4",4,"a6a3d",5,"8d8aa",7,"f1d94",136,"464c9",11,"2010b",12,"b4d38",13,"c4885",14,"ecc09",16,"1895b",200,"9b4fb",17,"e0682",18,"a4c52",19,"4e637",20,"353de"],"native":[0,"4b0ec",1,"2ca20",2,"a49e0"]}}